[
  {
    "name": "夏季装备",
    "list": [
      {
        "name": "👔 衣服",
        "list": [
          "🩲 一次性内裤",
          "👙 内衣",
          "🧥 睡衣",
          "防晒衣",
          "🩴 拖鞋",
          "墨镜",
          "日常衣物"
        ]
      },
      {
        "name": "📷 数码产品",
        "list": ["iPad", "MacBook💻", "🤳自拍杆", "排插", "充电线"]
      },
      {
        "name": "🪪 证件",
        "list": ["身份证", "银行卡"]
      },
      {
        "name": "🧺 卫生用品",
        "list": [
          "洗漱包",
          "牙刷、牙膏",
          "止血贴",
          "澡巾",
          "擦头巾",
          "剃须刀",
          "头箍",
          "纸巾、湿巾",
          "脏衣袋"
        ]
      },
      {
        "name": "🧴 美美",
        "list": [
          "卷发棒、发根棒",
          "防晒霜",
          "化妆包：粉底、腮红、眼影、口红、睫毛、眉工具",
          "护肤包：面膜、卸妆、洁面、眼唇",
          "吹风机"
        ]
      }
    ]
  },
  {
    "name": "冬季装备",
    "list": [
      {
        "name": "👔 衣服",
        "list": [
          "🩲 一次性内裤",
          "👙 内衣",
          "🧥 睡衣",
          "🩴 拖鞋",
          "羽绒服",
          "保暖内衣",
          "日常衣物",
          "暖宝宝"
        ]
      },
      {
        "name": "📷 数码产品",
        "list": ["iPad", "MacBook💻", "🤳自拍杆", "排插", "充电线"]
      },
      {
        "name": "🪪 证件",
        "list": ["身份证", "银行卡"]
      },
      {
        "name": "🧺 卫生用品",
        "list": [
          "洗漱包",
          "牙刷、牙膏",
          "止血贴",
          "澡巾",
          "擦头巾",
          "剃须刀",
          "头箍",
          "纸巾、湿巾",
          "脏衣袋"
        ]
      },
      {
        "name": "🧴 美美",
        "list": [
          "卷发棒、发根棒",
          "防晒霜",
          "化妆包：粉底、腮红、眼影、口红、睫毛、眉工具",
          "护肤包：面膜、卸妆、洁面、眼唇",
          "吹风机"
        ]
      }
    ]
  }
]
